rapthor/__init__.py
rapthor/_logging.py
rapthor/_version.py
rapthor/modifystate.py
rapthor/process.py
rapthor/lib/__init__.py
rapthor/lib/cluster.py
rapthor/lib/context.py
rapthor/lib/cwl.py
rapthor/lib/cwlrunner.py
rapthor/lib/facet.py
rapthor/lib/field.py
rapthor/lib/fitsimage.py
rapthor/lib/miscellaneous.py
rapthor/lib/observation.py
rapthor/lib/operation.py
rapthor/lib/parset.py
rapthor/lib/sector.py
rapthor/lib/strategy.py
rapthor/lib/toil_batch_systems/__init__.py
rapthor/lib/toil_batch_systems/toil_batch_system_slurm_static.py
rapthor/operations/__init__.py
rapthor/operations/calibrate.py
rapthor/operations/concatenate.py
rapthor/operations/image.py
rapthor/operations/mosaic.py
rapthor/operations/predict.py
rapthor/pipeline/execution/concat_ms.cwl
rapthor/pipeline/execution/fetch_data.cwl
rapthor/pipeline/execution/hba_nl.cwl
rapthor/pipeline/execution/run_rapthor.cwl
rapthor/pipeline/execution/tar_directory.cwl
rapthor/pipeline/execution/utils.js
rapthor/pipeline/execution/examples/hba_nl/L667526.config.json
rapthor/pipeline/execution/examples/hba_nl/hba_nl.json
rapthor/pipeline/execution/examples/hba_nl/hba_nl.sh
rapthor/pipeline/parsets/calibrate_di_pipeline.cwl
rapthor/pipeline/parsets/calibrate_pipeline.cwl
rapthor/pipeline/parsets/concatenate_pipeline.cwl
rapthor/pipeline/parsets/image_pipeline.cwl
rapthor/pipeline/parsets/image_sector_pipeline.cwl
rapthor/pipeline/parsets/mosaic_pipeline.cwl
rapthor/pipeline/parsets/mosaic_type_pipeline.cwl
rapthor/pipeline/parsets/predict_di_pipeline.cwl
rapthor/pipeline/parsets/predict_nc_pipeline.cwl
rapthor/pipeline/parsets/predict_pipeline.cwl
rapthor/pipeline/steps/add_sector_models.cwl
rapthor/pipeline/steps/adjust_h5parm_sources.cwl
rapthor/pipeline/steps/blank_image.cwl
rapthor/pipeline/steps/calculate_image_diagnostics.cwl
rapthor/pipeline/steps/collect_h5parms.cwl
rapthor/pipeline/steps/collect_screen_h5parms.cwl
rapthor/pipeline/steps/combine_h5parms.cwl
rapthor/pipeline/steps/compress_mosaic_image.cwl
rapthor-2.1.post1.dist-info/licenses/LICENSE
rapthor-2.1.post1.dist-info/METADATA
rapthor-2.1.post1.dist-info/WHEEL
rapthor-2.1.post1.dist-info/top_level.txt
rapthor-2.1.post1.dist-info/RECORD
