Metadata-Version: 2.4
Name: rapthor
Version: 2.1.post1
Summary: Rapthor: LOFAR DDE Pipeline
Author-email: David Rafferty <drafferty@hs.uni-hamburg.de>, Marcel Loose <loose@astron.nl>, Andre Offringa <offringa@astron.nl>, "Arend G. Dijkstra" <adijkstra@astron.nl>, Tammo Jan Dijkema <dijkema@astron.nl>, Mark de Wever <mark.dewever@stcorp.nl>, Frits Sweijen <sweijen@astron.nl>, Sarod Yatawatta <yatawatta@astron.nl>
License:                     GNU GENERAL PUBLIC LICENSE
Classifier: Development Status :: 4 - Beta
Classifier: Intended Audience :: Science/Research
Classifier: License :: OSI Approved :: GNU General Public License v3 (GPLv3)
Classifier: Natural Language :: English
Classifier: Operating System :: POSIX :: Linux
Classifier: Programming Language :: Python :: 3
Classifier: Topic :: Scientific/Engineering :: Astronomy
Requires-Python: >=3.9
License-File: LICENSE
Requires-Dist: astropy
Requires-Dist: bdsf
Requires-Dist: jinja2
Requires-Dist: losoto>=2.4.3
Requires-Dist: lsmtool>=1.8.0
Requires-Dist: matplotlib
Requires-Dist: mocpy
Requires-Dist: numpy
Requires-Dist: python-casacore
Requires-Dist: python-dateutil
Requires-Dist: pyyaml
Requires-Dist: reproject
Requires-Dist: requests
Requires-Dist: Rtree
Requires-Dist: scipy
Requires-Dist: shapely
Requires-Dist: toil[cwl]>=9.0
Requires-Dist: streamflow>=0.2.0.dev13
Provides-Extra: test
Requires-Dist: tox; extra == "test"
Dynamic: license-file
